wordpressupdater.py
wordpressupdater-0.5.16.dist-info/DESCRIPTION.rst
wordpressupdater-0.5.16.dist-info/METADATA
wordpressupdater-0.5.16.dist-info/RECORD
wordpressupdater-0.5.16.dist-info/WHEEL
wordpressupdater-0.5.16.dist-info/entry_points.txt
wordpressupdater-0.5.16.dist-info/metadata.json
wordpressupdater-0.5.16.dist-info/namespace_packages.txt
wordpressupdater-0.5.16.dist-info/top_level.txt
